livekit/plugins/murf/__init__.py
livekit/plugins/murf/log.py
livekit/plugins/murf/models.py
livekit/plugins/murf/py.typed
livekit/plugins/murf/tts.py
livekit/plugins/murf/version.py
livekit_murf-0.1.0.dist-info/METADATA
livekit_murf-0.1.0.dist-info/WHEEL
livekit_murf-0.1.0.dist-info/licenses/LICENSE
livekit_murf-0.1.0.dist-info/RECORD
