Metadata-Version: 2.4
Name: livekit-murf
Version: 0.1.0
Summary: LiveKit Agents Plugin for Murf
Project-URL: Repository, https://github.com/murf-ai/livekit-murf
Project-URL: Issues, https://github.com/murf-ai/livekit-murf/issues
Author-email: Gaurav Singh <gaurav.singh@murf.ai>
License-Expression: MIT
License-File: LICENSE
Keywords: audio,livekit,realtime,webrtc
Classifier: Intended Audience :: Developers
Classifier: License :: OSI Approved :: Apache Software License
Classifier: Programming Language :: Python :: 3
Classifier: Programming Language :: Python :: 3 :: Only
Classifier: Programming Language :: Python :: 3.9
Classifier: Programming Language :: Python :: 3.10
Classifier: Topic :: Multimedia :: Sound/Audio
Classifier: Topic :: Multimedia :: Video
Classifier: Topic :: Scientific/Engineering :: Artificial Intelligence
Requires-Python: >=3.9.0
Requires-Dist: livekit-agents>=1.2.18
